episode_names/__init__.py
episode_names/__main__.py
episode_names/app.py
episode_names/app_design.tcss
episode_names/Modals/DialogueModals.py
episode_names/Modals/EpisodeModals.py
episode_names/Modals/ProjectModals.py
episode_names/Modals/__init__.py
episode_names/Screens/EpisodesScreen.py
episode_names/Screens/SettingsScreen.py
episode_names/Screens/TemplateScreen.py
episode_names/Screens/__init__.py
episode_names/Utility/__init__.py
episode_names/Utility/command_palette.py
episode_names/Utility/custom_widgets.py
episode_names/Utility/db.py
episode_names/Utility/db_aux_utility.py
episode_names/Utility/db_operations.py
episode_names/Utility/i18n.py
episode_names/Utility/order.py
episode_names/external_internal/__init__.py
episode_names/external_internal/textual_autocomplete.py
episode_names-0.1.0rc0.dist-info/METADATA
episode_names-0.1.0rc0.dist-info/WHEEL
episode_names-0.1.0rc0.dist-info/entry_points.txt
episode_names-0.1.0rc0.dist-info/licenses/LICENSE
episode_names-0.1.0rc0.dist-info/RECORD
