Metadata-Version: 2.4
Name: episode-names
Version: 0.1.0rc0
Summary: A tool to manage and partially automize the title for episodic video titles and descriptions
Project-URL: Homepage, https://codeberg.org/BurnoutDV/EpisodeNames
Project-URL: Repository, https://codeberg.org/BurnoutDV/EpisodeNames
Project-URL: Issues, https://codeberg.org/BurnoutDV/EpisodeNames/issues
Project-URL: Documentation, https://codeberg.org/BurnoutDV/EpisodeNames/src/branch/master/README.md
Author-email: burnoutdv <development@burnoutdv.com>
License:                     GNU GENERAL PUBLIC LICENSE
License-File: LICENSE
Keywords: cli,episode_names,terminal,textual,tui
Classifier: Development Status :: 3 - Alpha
Classifier: Environment :: Console
Classifier: License :: OSI Approved :: GNU General Public License v3 or later (GPLv3+)
Classifier: Operating System :: MacOS
Classifier: Operating System :: Microsoft :: Windows
Classifier: Operating System :: POSIX :: Linux
Classifier: Programming Language :: Python
Classifier: Programming Language :: Python :: 3.11
Classifier: Programming Language :: Python :: 3.12
Classifier: Topic :: Utilities
Requires-Python: >=3.12
Requires-Dist: peewee==3.17.9
Requires-Dist: platformdirs>=4.3.7
Requires-Dist: pyperclip~=1.9.0
Requires-Dist: rich>=13.9.4
Requires-Dist: textual-autocomplete==4.0.4
Requires-Dist: textual-fspicker~=0.4.1
Requires-Dist: textual==3.0.0
